{
  "updated_at": "2026-06-25T13:21:23Z",
  "crypto": {
    "fear_greed": {
      "value": 12,
      "label": "Extreme Fear",
      "previous_value": 17,
      "previous_label": "Extreme Fear"
    },
    "prices": [
      {
        "symbol": "BTC",
        "name": "Bitcoin",
        "price_usd": 61224,
        "change_24h": -0.78,
        "market_cap": 1227500145847,
        "volume_24h": 44757517770
      },
      {
        "symbol": "ETH",
        "name": "Ethereum",
        "price_usd": 1634.88,
        "change_24h": -0.7,
        "market_cap": 197369993677,
        "volume_24h": 15794184310
      },
      {
        "symbol": "BNB",
        "name": "BNB",
        "price_usd": 564.58,
        "change_24h": -0.83,
        "market_cap": 76085984975,
        "volume_24h": 997896967
      },
      {
        "symbol": "XRP",
        "name": "XRP",
        "price_usd": 1.074,
        "change_24h": -0.64,
        "market_cap": 66630099096,
        "volume_24h": 2114471161
      },
      {
        "symbol": "SOL",
        "name": "Solana",
        "price_usd": 68.25,
        "change_24h": -0.76,
        "market_cap": 39614100261,
        "volume_24h": 3376353032
      },
      {
        "symbol": "DOGE",
        "name": "Dogecoin",
        "price_usd": 0.076002,
        "change_24h": -2.18,
        "market_cap": 11764278986,
        "volume_24h": 920243455
      },
      {
        "symbol": "LINK",
        "name": "Chainlink",
        "price_usd": 7.45,
        "change_24h": -1.02,
        "market_cap": 5572857045,
        "volume_24h": 288533934
      },
      {
        "symbol": "ADA",
        "name": "Cardano",
        "price_usd": 0.148066,
        "change_24h": 1.24,
        "market_cap": 5513875402,
        "volume_24h": 551987678
      },
      {
        "symbol": "AVAX",
        "name": "Avalanche",
        "price_usd": 6.36,
        "change_24h": 0.27,
        "market_cap": 2747644606,
        "volume_24h": 286317734
      }
    ],
    "top_mentioned": [
      {
        "symbol": "BTC",
        "mentions": 6,
        "price_usd": 61224,
        "change_24h": -0.78
      },
      {
        "symbol": "ETH",
        "mentions": 1,
        "price_usd": 1634.88,
        "change_24h": -0.7
      },
      {
        "symbol": "SOL",
        "mentions": 1,
        "price_usd": 68.25,
        "change_24h": -0.76
      },
      {
        "symbol": "BNB",
        "mentions": 1,
        "price_usd": 564.58,
        "change_24h": -0.83
      },
      {
        "symbol": "ADA",
        "mentions": 1,
        "price_usd": 0.148066,
        "change_24h": 1.24
      },
      {
        "symbol": "XRP",
        "mentions": 0,
        "price_usd": 1.074,
        "change_24h": -0.64
      },
      {
        "symbol": "DOGE",
        "mentions": 0,
        "price_usd": 0.076002,
        "change_24h": -2.18
      },
      {
        "symbol": "AVAX",
        "mentions": 0,
        "price_usd": 6.36,
        "change_24h": 0.27
      },
      {
        "symbol": "LINK",
        "mentions": 0,
        "price_usd": 7.45,
        "change_24h": -1.02
      },
      {
        "symbol": "TON",
        "mentions": 0,
        "price_usd": null,
        "change_24h": null
      }
    ],
    "news": [
      {
        "title": "CoinDesk 20 performance update: AAVE gains 10.1% as index rises",
        "source": "CoinDesk",
        "url": "https://www.coindesk.com/coindesk-indices/2026/06/25/coindesk-20-performance-update-aave-gains-10-1-as-index-rises",
        "published": "Thu, 25 Jun 2026 13:15:26 +0000",
        "assets": [],
        "sentiment": "Bullish",
        "score": 0.8,
        "color": "green"
      },
      {
        "title": "Uniswap, Spark aim to build stablecoin FX market as banks, fintechs enter the industry",
        "source": "CoinDesk",
        "url": "https://www.coindesk.com/business/2026/06/25/uniswap-spark-aim-to-build-stablecoin-fx-market-as-banks-fintechs-enter-the-industry",
        "published": "Thu, 25 Jun 2026 13:00:00 +0000",
        "assets": [
          "UNI"
        ],
        "sentiment": "Bullish",
        "score": 0.6,
        "color": "green"
      },
      {
        "title": "Post-prison CZ says time behind bars didn't hurt the billionaire's business after Binance",
        "source": "CoinDesk",
        "url": "https://www.coindesk.com/policy/2026/06/24/post-prison-cz-says-time-behind-bars-didn-t-hurt-the-billionaire-s-business-after-binance",
        "published": "Thu, 25 Jun 2026 13:00:00 +0000",
        "assets": [],
        "sentiment": "Bullish",
        "score": 0.4,
        "color": "green"
      },
      {
        "title": "Circle and Nomura join forces to target a $440 billion daily foreign exchange market in Japan",
        "source": "CoinDesk",
        "url": "https://www.coindesk.com/markets/2026/06/25/circle-and-nomura-join-forces-to-target-a-usd750-billion-daily-foreign-exchange-market-in-japan",
        "published": "Thu, 25 Jun 2026 12:29:21 +0000",
        "assets": [],
        "sentiment": "Bullish",
        "score": 0.7,
        "color": "green"
      },
      {
        "title": "Bitcoin derivatives signal panic. A weak core PCE reading could trigger snapback.",
        "source": "CoinDesk",
        "url": "https://www.coindesk.com/daybook-us/2026/06/25/bitcoin-derivatives-signal-panic-a-weak-core-pce-reading-could-trigger-snapback",
        "published": "Thu, 25 Jun 2026 11:31:02 +0000",
        "assets": [
          "BTC"
        ],
        "sentiment": "Bearish",
        "score": -0.5,
        "color": "red"
      },
      {
        "title": "CoinEx denies claims it served as $3.84 billion gateway to sanctioned Iranian crypto firms",
        "source": "CoinDesk",
        "url": "https://www.coindesk.com/policy/2026/06/25/coinex-denies-claims-it-served-as-usd3-84-billion-gateway-to-sanctioned-iranian-crypto-firms",
        "published": "Thu, 25 Jun 2026 10:56:58 +0000",
        "assets": [],
        "sentiment": "Bearish",
        "score": -0.3,
        "color": "red"
      },
      {
        "title": "Crypto relief rally fails to shake persistent bearish derivatives signal",
        "source": "CoinDesk",
        "url": "https://www.coindesk.com/markets/2026/06/25/crypto-relief-rally-fails-to-shake-persistent-bearish-derivatives-signal",
        "published": "Thu, 25 Jun 2026 10:53:24 +0000",
        "assets": [],
        "sentiment": "Bearish",
        "score": -0.6,
        "color": "red"
      },
      {
        "title": "Bitcoin supply in loss reaches record high 10.83 million BTC",
        "source": "CoinDesk",
        "url": "https://www.coindesk.com/markets/2026/06/25/bitcoin-supply-in-loss-reaches-record-high-10-83-million-btc",
        "published": "Thu, 25 Jun 2026 10:28:37 +0000",
        "assets": [
          "BTC"
        ],
        "sentiment": "Bearish",
        "score": -0.8,
        "color": "red"
      },
      {
        "title": "Micron delivers blowout earnings, surges 16% and deals crypto bulls a blow",
        "source": "CoinDesk",
        "url": "https://www.coindesk.com/markets/2026/06/25/micron-delivers-blowout-earnings-surges-16-and-deals-crypto-bulls-a-blow",
        "published": "Thu, 25 Jun 2026 10:01:54 +0000",
        "assets": [],
        "sentiment": "Bearish",
        "score": -0.4,
        "color": "red"
      },
      {
        "title": "Forget max pain theory. Bitcoin is well below the $72,000 magnet going into $10 billion options expiry",
        "source": "CoinDesk",
        "url": "https://www.coindesk.com/markets/2026/06/25/forget-max-pain-bitcoin-is-well-below-the-usd72-000-magnet-ahead-of-usd10-billion-options-expiry",
        "published": "Thu, 25 Jun 2026 07:24:59 +0000",
        "assets": [
          "BTC"
        ],
        "sentiment": "Bearish",
        "score": -0.3,
        "color": "red"
      },
      {
        "title": "Here’s what happened in crypto today",
        "source": "Cointelegraph",
        "url": "https://cointelegraph.com/news/what-happened-in-crypto-today?utm_source=rss&utm_medium=rss&utm_campaign=rss",
        "published": "Thu, 25 Jun 2026 13:19:46 GMT",
        "assets": [],
        "sentiment": "Neutral",
        "score": 0.0,
        "color": "yellow"
      },
      {
        "title": "SBI to acquire Bitbank in $289M deal creating Japan's biggest crypto exchange",
        "source": "Cointelegraph",
        "url": "https://cointelegraph.com/news/sbi-acquire-bitbank-289-million-deal?utm_source=rss&utm_medium=rss&utm_campaign=rss",
        "published": "Thu, 25 Jun 2026 13:08:11 GMT",
        "assets": [],
        "sentiment": "Bullish",
        "score": 0.7,
        "color": "green"
      },
      {
        "title": "About 60% of World Cup bettors on Polymarket are first-time crypto users",
        "source": "Cointelegraph",
        "url": "https://cointelegraph.com/news/polymarket-first-crypto-touchpoint-world-cup-bettors?utm_source=rss&utm_medium=rss&utm_campaign=rss",
        "published": "Thu, 25 Jun 2026 13:00:00 GMT",
        "assets": [],
        "sentiment": "Bullish",
        "score": 0.6,
        "color": "green"
      },
      {
        "title": "Spark migrates $150M in stablecoin to Uniswap to advance shared liquidity",
        "source": "Cointelegraph",
        "url": "https://cointelegraph.com/news/spark-deploys-150m-stablecoin-liquidity-uniswap-v4?utm_source=rss&utm_medium=rss&utm_campaign=rss",
        "published": "Thu, 25 Jun 2026 13:00:00 GMT",
        "assets": [
          "UNI"
        ],
        "sentiment": "Bullish",
        "score": 0.5,
        "color": "green"
      },
      {
        "title": "Binance faces EU service limits next week as MiCA rules take effect",
        "source": "Cointelegraph",
        "url": "https://cointelegraph.com/news/binance-eu-service-limits-july-1-mica-effect?utm_source=rss&utm_medium=rss&utm_campaign=rss",
        "published": "Thu, 25 Jun 2026 12:19:32 GMT",
        "assets": [],
        "sentiment": "Bearish",
        "score": -0.6,
        "color": "red"
      }
    ],
    "news_sentiment": {
      "score": 0.053,
      "label": "Neutral",
      "color": "yellow"
    },
    "polymarket": [
      {
        "title": "Will Netherlands win on 2026-06-25?",
        "volume_24h": 984526,
        "yes_price": 0.9,
        "category": "crypto"
      },
      {
        "title": "Will Bitcoin dip to $57,500 in June?",
        "volume_24h": 333458,
        "yes_price": 0.25,
        "category": "crypto"
      },
      {
        "title": "Will the price of Bitcoin be above $60,000 on June 25?",
        "volume_24h": 274279,
        "yes_price": 0.93,
        "category": "crypto"
      },
      {
        "title": "Bitcoin Up or Down on June 25?",
        "volume_24h": 223193,
        "yes_price": 0.91,
        "category": "crypto"
      }
    ],
    "polymarket_summary": {
      "outlook": "Bullish",
      "summary": "Bullish: Market sentiment for Bitcoin is strongly positive, with a 93% probability that the price will be above $60,000 on June 25 and a 91% chance it will move up. Conversely, only 25% of traders expect a dip to $57,500 in June. While unrelated to crypto, the Netherlands is heavily favored to win on June 25 with 90% confidence and significant volume of $984,526."
    },
    "reddit": [
      {
        "subreddit": "r/CryptoCurrency",
        "mentions": {
          "BTC": 6,
          "ETH": 1,
          "SOL": 1,
          "BNB": 1,
          "ADA": 1,
          "XRP": 0,
          "DOGE": 0,
          "AVAX": 0,
          "LINK": 0,
          "TON": 0
        },
        "activity_score": 100,
        "top_post": "Daily Crypto Discussion - June 24, 2026 (GMT+0)",
        "top_post_url": "https://old.reddit.com/r/CryptoCurrency/comments/1uesvmz/daily_crypto_discussion_june_24_2026_gmt0/",
        "top_post_score": 0,
        "posts": 25
      }
    ],
    "reddit_summary": {
      "outlook": "Mixed",
      "summary": "Mixed: Sentiment is fragmented despite high activity (100/100) in r/CryptoCurrency. While BTC dominates the conversation with 6 mentions, indicating strong focus on the market leader, the presence of ETH, SOL, BNB, and ADA (1 mention each) suggests a diversified but cautious interest across altcoins. The lack of overwhelming consensus on a single direction suggests investors are weighing BTC's dominance against broader market volatility."
    },
    "news_summary": {
      "outlook": "Mixed",
      "summary": "We need exactly ONE paragraph, start with 'Bullish:', 'Bearish:', or 'Mixed:' followed by specific reasons. Mention numbers and names where available. Max 80 words.\n\nWe need to decide overall sentiment based on data: many bullish items (CoinDesk 20, Uniswap/Spark, CZ, Circle/Nomura) and bearish items (Bitcoin derivatives panic, CoinEx denial, relief rally fails, Bitcoin supply in loss record high). Mixed? Probably mixed sentiment. So start with \"Mixed:\" then list reasons with numbers/names.\n\nWe need to keep under 80 words. Let's craft ~70 words.\n\nParagraph: Mixed: ... include numbers: AAVE +10.1%, $440bn daily FX market, 10.83 million BTC in loss, $3.84bn gateway claim, etc.\n\nWord count: Let's draft ~65 words.\n\n\"Mixed: CoinDesk 20 shows AAVE up 10.1% while Uniswap and Spark plan a stablecoin FX arena and Circle‑Nomura target Japan’s $440 billion daily FX market, and former Binance CEO CZ claims prison didn’t dent his business. Conversely, Bitcoin derivatives flash panic, a weak core PCE could spark a snapback, CoinEx denies a $3.84 bn sanctioned‑Iran gateway"
    },
    "fourchain": {
      "thread_count": 201,
      "active_threads": 129,
      "mentions": {
        "BTC": 29,
        "XRP": 8,
        "ETH": 3
      },
      "bullish_hits": 75,
      "bearish_hits": 47,
      "bullish_pct": 61,
      "top_coin": "BTC"
    },
    "cg_trending": [
      {
        "symbol": "M",
        "name": "MemeCore",
        "rank": 65,
        "score": 0,
        "change_24h": -72.62
      },
      {
        "symbol": "ZANO",
        "name": "Zano",
        "rank": 191,
        "score": 1,
        "change_24h": 7.52
      },
      {
        "symbol": "SYN",
        "name": "Synapse",
        "rank": 249,
        "score": 2,
        "change_24h": 66.21
      },
      {
        "symbol": "CARDS",
        "name": "Collector Crypt",
        "rank": 290,
        "score": 3,
        "change_24h": 9.64
      },
      {
        "symbol": "RAIN",
        "name": "Rain",
        "rank": 13,
        "score": 4,
        "change_24h": -1.36
      },
      {
        "symbol": "BTC",
        "name": "Bitcoin",
        "rank": 1,
        "score": 5,
        "change_24h": -1.29
      },
      {
        "symbol": "PENGU",
        "name": "Pudgy Penguins",
        "rank": 118,
        "score": 6,
        "change_24h": -1.29
      }
    ]
  },
  "stocks": {
    "indices": {
      "sp500": {
        "value": 7358.22,
        "change_24h": -0.1
      },
      "nasdaq": {
        "value": 25476.64,
        "change_24h": -0.43
      },
      "dow": {
        "value": 51848.9,
        "change_24h": 0.35
      },
      "vix": {
        "value": 17.89,
        "change_24h": -3.97
      }
    },
    "market_mood": {
      "score": -0.35,
      "label": "Bearish",
      "color": "red"
    },
    "prices": [
      {
        "symbol": "NVDA",
        "price_usd": 199.0,
        "change_24h": -0.52
      },
      {
        "symbol": "TSLA",
        "price_usd": 375.53,
        "change_24h": -1.59
      },
      {
        "symbol": "AAPL",
        "price_usd": 293.08,
        "change_24h": -0.41
      },
      {
        "symbol": "MSFT",
        "price_usd": 365.46,
        "change_24h": -2.27
      },
      {
        "symbol": "GOOGL",
        "price_usd": 345.29,
        "change_24h": -0.24
      },
      {
        "symbol": "AMZN",
        "price_usd": 234.27,
        "change_24h": 0.07
      },
      {
        "symbol": "META",
        "price_usd": 557.67,
        "change_24h": -0.81
      },
      {
        "symbol": "AMD",
        "price_usd": 519.74,
        "change_24h": -0.02
      },
      {
        "symbol": "PLTR",
        "price_usd": 113.5,
        "change_24h": -2.74
      },
      {
        "symbol": "COIN",
        "price_usd": 150.11,
        "change_24h": -5.1
      }
    ],
    "top_mentioned": [],
    "news": [
      {
        "title": "Core inflation rate hit 3.4% in May, highest since October 2023, Fed’s preferred gauge shows",
        "source": "CNBC",
        "url": "https://www.cnbc.com/2026/06/25/pce-inflation-report-may-2026-.html",
        "published": "Thu, 25 Jun 2026 12:56:48 GMT",
        "assets": [],
        "sentiment": "Bearish",
        "score": -0.7,
        "color": "red"
      },
      {
        "title": "Apple raises prices on MacBook and iPad due to memory crunch, hints at more to come",
        "source": "CNBC",
        "url": "https://www.cnbc.com/2026/06/25/apple-macbook-ipad-price-hike-memory.html",
        "published": "Thu, 25 Jun 2026 13:04:19 GMT",
        "assets": [
          "AAPL"
        ],
        "sentiment": "Bearish",
        "score": -0.4,
        "color": "red"
      },
      {
        "title": "JPMorgan names Doug Petno and Troy Rohrbaugh co-presidents as longtime exec Marianne Lake exits",
        "source": "CNBC",
        "url": "https://www.cnbc.com/2026/06/25/jpmorgan-chase-co-presidents-lake-exits.html",
        "published": "Thu, 25 Jun 2026 13:19:26 GMT",
        "assets": [],
        "sentiment": "Neutral",
        "score": 0.0,
        "color": "yellow"
      },
      {
        "title": "Wendy's shares soar for a second day as retail investors pile into their new meme darling",
        "source": "CNBC",
        "url": "https://www.cnbc.com/2026/06/25/wendys-shares-soar-for-a-second-day-as-retail-investors-pile-into-their-new-meme-darling.html",
        "published": "Thu, 25 Jun 2026 13:19:23 GMT",
        "assets": [],
        "sentiment": "Bullish",
        "score": 0.9,
        "color": "green"
      },
      {
        "title": "GameStop’s CEO just sacrificed a $35 billion pay package. Here’s how it could impact his effort to buy eBay",
        "source": "CNBC",
        "url": "https://www.cnbc.com/2026/06/25/gamestops-ceo-sacrificed-pay-it-could-impact-the-effort-to-buy-ebay-.html",
        "published": "Thu, 25 Jun 2026 12:07:50 GMT",
        "assets": [
          "GME"
        ],
        "sentiment": "Neutral",
        "score": -0.2,
        "color": "yellow"
      },
      {
        "title": "Chevron says no quick fix for gas prices as Trump takes on Big Oil: ‘It’s going to take time’",
        "source": "CNBC",
        "url": "https://www.cnbc.com/2026/06/25/chevron-gas-prices-trump-big-oil.html",
        "published": "Thu, 25 Jun 2026 12:16:48 GMT",
        "assets": [],
        "sentiment": "Bearish",
        "score": -0.3,
        "color": "red"
      },
      {
        "title": "Iraq piles pressure on OPEC over quota dispute after UAE exit",
        "source": "CNBC",
        "url": "https://www.cnbc.com/2026/06/25/iraq-opec-oil-supply-quota-exports-subdued.html",
        "published": "Thu, 25 Jun 2026 11:58:16 GMT",
        "assets": [],
        "sentiment": "Bearish",
        "score": -0.5,
        "color": "red"
      },
      {
        "title": "The world’s top-performing stock market still isn’t a developed market. Here’s why, according to the MSCI chief",
        "source": "CNBC",
        "url": "https://www.cnbc.com/2026/06/25/south-korea-emerging-market-developed-msci-kospi.html",
        "published": "Thu, 25 Jun 2026 13:13:57 GMT",
        "assets": [],
        "sentiment": "Neutral",
        "score": 0.2,
        "color": "yellow"
      },
      {
        "title": "Darden Restaurants earnings beat estimates but Olive Garden growth weakens",
        "source": "CNBC",
        "url": "https://www.cnbc.com/2026/06/25/darden-restaurants-dri-q4-2026-earnings.html",
        "published": "Thu, 25 Jun 2026 12:27:13 GMT",
        "assets": [],
        "sentiment": "Neutral",
        "score": 0.1,
        "color": "yellow"
      },
      {
        "title": "TikTok and YouTube are reinventing sports viewership. Broadcasters are taking note",
        "source": "CNBC",
        "url": "https://www.cnbc.com/2026/06/25/tiktok-youtube-sports-viewership.html",
        "published": "Thu, 25 Jun 2026 11:00:01 GMT",
        "assets": [],
        "sentiment": "Bullish",
        "score": 0.4,
        "color": "green"
      },
      {
        "title": "Rocket Lab, Lockheed Martin among the partners in SpaceX’s military space-laser project",
        "source": "MarketWatch",
        "url": "https://www.marketwatch.com/story/rocket-lab-lockheed-martin-among-the-partners-in-spacexs-military-space-laser-project-1b8d61e2?mod=mw_rss_topstories",
        "published": "Thu, 25 Jun 2026 13:06:00 GMT",
        "assets": [],
        "sentiment": "Bullish",
        "score": 0.6,
        "color": "green"
      },
      {
        "title": "I had gallbladder surgery. After I got home, the hospital asked me for a financial donation. Is this ethical?",
        "source": "MarketWatch",
        "url": "https://www.marketwatch.com/story/i-had-my-gallbladder-removed-after-i-got-home-the-hospital-asked-me-for-a-donation-is-this-ethical-ad12a8e1?mod=mw_rss_topstories",
        "published": "Thu, 25 Jun 2026 13:01:00 GMT",
        "assets": [],
        "sentiment": "Neutral",
        "score": 0.0,
        "color": "yellow"
      },
      {
        "title": "These S&P 500 stocks are expected to make double-digit comebacks",
        "source": "MarketWatch",
        "url": "https://www.marketwatch.com/story/these-s-p-500-stocks-are-expected-to-make-double-digit-comebacks-8696a849?mod=mw_rss_topstories",
        "published": "Thu, 25 Jun 2026 12:51:00 GMT",
        "assets": [
          "SPY"
        ],
        "sentiment": "Bullish",
        "score": 0.8,
        "color": "green"
      },
      {
        "title": "Consumer spending rises again — and now cheaper gas is on the way",
        "source": "MarketWatch",
        "url": "https://www.marketwatch.com/story/consumer-spending-rises-again-and-now-cheaper-gas-is-on-the-way-7615b45b?mod=mw_rss_topstories",
        "published": "Thu, 25 Jun 2026 12:50:00 GMT",
        "assets": [],
        "sentiment": "Bullish",
        "score": 0.7,
        "color": "green"
      },
      {
        "title": "Here are five themes Wall Street left behind while chasing a single trade",
        "source": "MarketWatch",
        "url": "https://www.marketwatch.com/story/here-are-five-themes-wall-street-left-behind-while-chasing-a-single-trade-2fc5a2ab?mod=mw_rss_topstories",
        "published": "Thu, 25 Jun 2026 12:44:00 GMT",
        "assets": [],
        "sentiment": "Neutral",
        "score": -0.2,
        "color": "yellow"
      }
    ],
    "news_sentiment": {
      "score": 0.093,
      "label": "Neutral",
      "color": "yellow"
    },
    "polymarket": [
      {
        "title": "Will Cole Young win the 2026 AL Platinum Glove award?",
        "volume_24h": 371974,
        "yes_price": 0.04,
        "category": "finance"
      },
      {
        "title": "Will the Fed increase interest rates by 25 bps after the July 2026 meeting?",
        "volume_24h": 256863,
        "yes_price": 0.22,
        "category": "finance"
      },
      {
        "title": "Will there be no change in Fed interest rates after the July 2026 meeting?",
        "volume_24h": 237408,
        "yes_price": 0.77,
        "category": "finance"
      }
    ],
    "polymarket_summary": {
      "outlook": "Bearish",
      "summary": "Bearish: Market sentiment is overwhelmingly negative regarding Cole Young winning the 2026 AL Platinum Glove, with only a 4% \"Yes\" probability. Regarding monetary policy, the market is bullish on stability, as 77% of traders expect no change in Fed interest rates after the July 2026 meeting, while only 22% anticipate a 25 bps increase. Trading volume remains significant across all markets, particularly for Young at $371,974."
    },
    "reddit": [],
    "reddit_summary": {
      "outlook": "Mixed",
      "summary": "We need to produce exactly ONE paragraph, starting with 'Bullish:', 'Bearish:', or 'Mixed:' followed by specific reasons. Must mention numbers and names where available. Max 80 words.\n\nData given: \"Top mentioned: Subreddits:\" but no actual data? The user gave incomplete data. Possibly they expect us to infer? But we have no numbers or names. We must still produce a paragraph with numbers and names where available. Since none are provided, we can say none available? But must mention numbers and names where available. If none, we can say \"No specific numbers or names were mentioned.\" That still mentions that none were available. But maybe we should say \"No numbers or names were provided.\" That is still mentioning that none were available. The instruction: \"Mention numbers and names where available.\" If none, we can note that none were provided. That satisfies.\n\nWe need to start with Bullish:, Bearish:, or Mixed:. Based on no data, we cannot determine sentiment. Probably Mixed: because insufficient info. Provide reasons: lack of clear sentiment, no specific tickers, etc.\n\nWord count max 80. Let's craft ~30 words.\n\n\"Mixed: The Reddit discussion did not highlight any specific stocks, tickers, or numerical metrics, making it impossible to discern a clear bullish or bearish bias; sentiment remains ambiguous due to absent concrete data.\"\n\nCount words: Mixed:(1)"
    },
    "news_summary": {
      "outlook": "Mixed",
      "summary": "We need exactly one paragraph, start with Bullish:, Bearish:, or Mixed: followed by specific reasons. Must mention numbers and names where available. Max 80 words. Summarize overall market sentiment. Based on data: many bearish items (core inflation 3.4%, Apple price hikes, Chevron gas prices, Iraq OPEC pressure). Bullish: Wendy's shares soar. Neutral items: JPMorgan exec changes, GameStop CEO pay package, MSCI comment. Overall sentiment likely mixed but leaning bearish. Choose Mixed: with reasons. Must be one paragraph, start with \"Mixed:\" then reasons. Include numbers and names: core inflation 3.4% (May), Apple price hikes, Wendy's shares soar, Chevron gas prices, Iraq OPEC quota dispute, JPMorgan names Doug Petno and Troy Rohrbaugh co-presidents as Marianne Lake exits, GameStop CEO sacrificed $35B pay package, MSCI comment. Keep under 80 words. Let's craft ~70 words.\n\nWord count: Let's draft:\n\n\"Mixed: Core inflation rose to 3.4% in May, the highest since October 2023, pressuring the Fed; Apple raised MacBook and iPad prices due to a memory crunch; Chevron warned gas prices won’t fall quickly amid Trump’s Big Oil scrutiny; Iraq piled pressure on OPEC after the UAE’s quota exit."
    },
    "macro": [
      {
        "symbol": "^TNX",
        "name": "10Y Treasury Yield",
        "value": 4.38,
        "change_24h": -1.64
      },
      {
        "symbol": "DX-Y.NYB",
        "name": "US Dollar Index",
        "value": 101.62,
        "change_24h": 0.01
      },
      {
        "symbol": "GC=F",
        "name": "Gold",
        "value": 4042.9,
        "change_24h": 1.32
      },
      {
        "symbol": "CL=F",
        "name": "Crude Oil",
        "value": 69.8,
        "change_24h": -0.77
      }
    ],
    "most_active": [
      {
        "symbol": "NVDA",
        "volume": 150824300,
        "price_usd": 199.0,
        "change_24h": -0.52
      },
      {
        "symbol": "AMZN",
        "volume": 70056700,
        "price_usd": 234.27,
        "change_24h": 0.07
      },
      {
        "symbol": "SPY",
        "volume": 56924000,
        "price_usd": 733.24,
        "change_24h": -0.05
      },
      {
        "symbol": "AAPL",
        "volume": 52882100,
        "price_usd": 293.08,
        "change_24h": -0.41
      },
      {
        "symbol": "QQQ",
        "volume": 52179200,
        "price_usd": 710.62,
        "change_24h": -0.42
      },
      {
        "symbol": "PLTR",
        "volume": 46237700,
        "price_usd": 113.5,
        "change_24h": -2.74
      },
      {
        "symbol": "GOOGL",
        "volume": 44821900,
        "price_usd": 345.29,
        "change_24h": -0.24
      },
      {
        "symbol": "MSFT",
        "volume": 44307200,
        "price_usd": 365.46,
        "change_24h": -2.27
      },
      {
        "symbol": "TSLA",
        "volume": 36926400,
        "price_usd": 375.53,
        "change_24h": -1.59
      },
      {
        "symbol": "BAC",
        "volume": 30286400,
        "price_usd": 57.73,
        "change_24h": -0.31
      }
    ],
    "google_trends": {
      "stocks": [],
      "crypto": []
    }
  },
  "portfolio": [
    {
      "symbol": "BKHY",
      "name": "BlackRock High Yield Bond",
      "type": "Bond Income",
      "price_usd": 47.47,
      "change_1d": -0.01,
      "change_1w": -0.26,
      "change_1m": 0.44,
      "high_3m": 47.65,
      "low_3m": 45.95,
      "week52_high": 48.89,
      "week52_low": 46.84,
      "rsi": 51.9,
      "div_yield": 7.38,
      "last_div": null,
      "outlook": {
        "label": "Mild Bullish",
        "color": "green",
        "score": 2,
        "bull_count": 2,
        "bear_count": 0,
        "total": 5,
        "confidence": "Low",
        "reasons": [
          "Price above 20-day moving average ↑",
          "Short-term trend above long-term (bullish cross) ↑",
          "RSI 51.9 — In neutral range (45–55)",
          "5-day momentum -0.3% — consolidating sideways →",
          "1-month return +0.4% — range-bound"
        ]
      }
    },
    {
      "symbol": "XYLD",
      "name": "Global X S&P 500 Covered Call",
      "type": "Covered Call Income",
      "price_usd": 40.22,
      "change_1d": -0.02,
      "change_1w": -0.91,
      "change_1m": 0.34,
      "high_3m": 40.61,
      "low_3m": 37.34,
      "week52_high": 41.1,
      "week52_low": 38.22,
      "rsi": 46.8,
      "div_yield": 10.53,
      "last_div": null,
      "outlook": {
        "label": "Neutral",
        "color": "yellow",
        "score": 0,
        "bull_count": 1,
        "bear_count": 1,
        "total": 5,
        "confidence": "Low",
        "reasons": [
          "Price below 20-day moving average ↓",
          "Short-term trend above long-term (bullish cross) ↑",
          "RSI 46.8 — In neutral range (45–55)",
          "5-day momentum -0.9% — consolidating sideways →",
          "1-month return +0.3% — range-bound"
        ]
      }
    },
    {
      "symbol": "JEPQ",
      "name": "JPMorgan Nasdaq Equity Premium",
      "type": "Equity Income",
      "price_usd": 59.69,
      "change_1d": -0.28,
      "change_1w": -1.79,
      "change_1m": 0.06,
      "high_3m": 61.38,
      "low_3m": 52.21,
      "week52_high": 61.72,
      "week52_low": 53.51,
      "rsi": 44.9,
      "div_yield": 10.11,
      "last_div": null,
      "outlook": {
        "label": "Mild Bearish",
        "color": "red",
        "score": -2,
        "bull_count": 1,
        "bear_count": 3,
        "total": 5,
        "confidence": "Medium",
        "reasons": [
          "Price below 20-day moving average ↓",
          "Short-term trend above long-term (bullish cross) ↑",
          "RSI 44.9 — Below neutral, mild downward pressure ↓",
          "5-day momentum -1.8% — short-term selling pressure ↓",
          "1-month return +0.1% — range-bound"
        ]
      }
    },
    {
      "symbol": "SCHD",
      "name": "Schwab US Dividend Equity",
      "type": "Dividend Growth",
      "price_usd": 31.72,
      "change_1d": -0.15,
      "change_1w": -1.71,
      "change_1m": -2.61,
      "high_3m": 32.57,
      "low_3m": 30.2,
      "week52_high": 32.92,
      "week52_low": 26.21,
      "rsi": 42.0,
      "div_yield": 3.25,
      "last_div": null,
      "outlook": {
        "label": "Mild Bearish",
        "color": "red",
        "score": -2,
        "bull_count": 1,
        "bear_count": 3,
        "total": 5,
        "confidence": "Medium",
        "reasons": [
          "Price below 20-day moving average ↓",
          "Short-term trend above long-term (bullish cross) ↑",
          "RSI 42.0 — Below neutral, mild downward pressure ↓",
          "5-day momentum -1.7% — short-term selling pressure ↓",
          "1-month return -2.6% — range-bound"
        ]
      }
    },
    {
      "symbol": "QQQM",
      "name": "Invesco Nasdaq 100",
      "type": "Growth",
      "price_usd": 292.63,
      "change_1d": -0.42,
      "change_1w": -2.53,
      "change_1m": -0.84,
      "high_3m": 306.87,
      "low_3m": 229.6,
      "week52_high": 308.21,
      "week52_low": 222.9,
      "rsi": 41.2,
      "div_yield": 42.0,
      "last_div": null,
      "outlook": {
        "label": "Mild Bearish",
        "color": "red",
        "score": -2,
        "bull_count": 1,
        "bear_count": 3,
        "total": 5,
        "confidence": "Medium",
        "reasons": [
          "Price below 20-day moving average ↓",
          "Short-term trend above long-term (bullish cross) ↑",
          "RSI 41.2 — Below neutral, mild downward pressure ↓",
          "5-day momentum -2.5% — short-term selling pressure ↓",
          "1-month return -0.8% — range-bound"
        ]
      }
    }
  ]
}